cavsiopy/__init__.py
cavsiopy/attitude_analysis.py
cavsiopy/attitude_plotter.py
cavsiopy/ephemeris_importer.py
cavsiopy/miscellaneous.py
cavsiopy/use_rotation_matrices.py
cavsiopy/coefficient_files/38_EOP_C01.1900-NOW_V2013_0138.txt
cavsiopy/coefficient_files/IERS_daily_deltaT.txt
cavsiopy-1.2.2.dist-info/METADATA
cavsiopy-1.2.2.dist-info/WHEEL
cavsiopy-1.2.2.dist-info/licenses/LICENSE
cavsiopy-1.2.2.dist-info/RECORD
