Metadata-Version: 2.1
Name: cavsiopy
Version: 1.2.2
Summary: A Python package to Calculate and Visualize Spacecraft Instrument Orientation
Project-URL: Homepage, https://github.com/icebearcanada/cavsiopy
Project-URL: Repository, https://github.com/icebearcanada/cavsiopy
Project-URL: Bug Tracker, https://github.com/icebearcanada/cavsiopy/issues
Project-URL: Documentation, https://readthedocs.org/projects/cavsiopy/
Author: E. Ceren Kalafatoglu Eyiguler, Warren Holley, Andrew D. Howarth, Donald W. Danskin, Kuldeep Pandey, Carley J. Martin, Glenn C. Hussey, Robert G. Gillies, Andrew W. Yau
License:                    GNU LESSER GENERAL PUBLIC LICENSE
License-File: LICENSE
Classifier: Development Status :: 4 - Beta
Classifier: Intended Audience :: Science/Research
Classifier: License :: OSI Approved :: MIT License
Classifier: Operating System :: OS Independent
Classifier: Programming Language :: Python
Classifier: Programming Language :: Python :: 3
Classifier: Programming Language :: Python :: 3 :: Only
Classifier: Programming Language :: Python :: 3.6
Classifier: Programming Language :: Python :: 3.7
Classifier: Programming Language :: Python :: 3.8
Classifier: Programming Language :: Python :: 3.9
Classifier: Topic :: Scientific/Engineering
Classifier: Topic :: Scientific/Engineering :: Visualization
Classifier: Topic :: Utilities
Requires-Python: >=3.4
